{
    "publications": [
        {
            "id": "meta-tokenization-transformers",
            "type": "Journal",
            "title": "Transformers and Meta-Tokenization in Sentiment Analysis for Software Engineering",
            "authors": [
                "Nathan Cassee",
                "Andrei Agaronian",
                "Eleni Constantinou",
                "Nicole Novielli", 
                "Alexander Serebrenik"
            ],
            "venue": "Empirical Software Engineering (EMSE)",
            "date": "2024-02-16",
            "filename": "meta-tokenization-transformers.pdf"
        },
        {
            "id": "saner-rene-replication",
            "type": "Conference",
            "title": "Sentiment of Technical Debt Security Questions on Stack Overflow: A Replication Study",
            "authors": [
                "Jarl Jansen",
                "Nathan Cassee",
                "Alexander Serebrenik"
            ],
            "venue": "IEEE International Conference on Software Analysis, Evolution and Reengineering (SANER), Reproducibility Studies and Negative Results (RENE) Track",
            "date": "2024-03-15",
            "filename": "rene-replication-sentiment.pdf"
        },
        {
            "id": "acquired-taste",
            "type": "Conference",
            "title": "Autonomy Is An Acquired Taste: Exploring Developer Preferences for GitHub Bots",
            "authors": [
                "Amir Ghorbani",
                "Nathan Cassee",
                "Derek Robinson",
                "Adam Alami",
                "Neil Ernst",
                "Alexander Serebrenik",
                "Andrzej Wasowski"
            ],
            "venue": "IEEE/ACM International Conference on Software Engineering (ICSE)",
            "filename": "acquired-taste.pdf",
            "date": "2023-05-14"
        },
        {
            "id": "asfbot",
            "type": "Conference",
            "title": "Between JIRA and GitHub: ASFBot and its Influence on Human Comments in Issue Trackers",
            "authors": [
                "Ambarish Moharil",
                "Dimitrii Orlov",
                "Samar Jameel",
                "Tristan Trouwen",
                "Nathan Cassee",
                "Alexander Serebrenik"
            ],
            "venue": "IEEE/ACM International Conference on Mining Software Repositories (MSR), Mining Challenge",
            "filename": "asfbot.pdf",
            "date": "2022-05-24"
        },
        {
            "id": "om-slr",
            "type": "Journal",
            "title": "Opinion Mining for Software Development: A Systematic Literature Review",
            "authors": [
                "Bin Lin",
                "Nathan Cassee",
                "Alexander Serebrenik", 
                "Gabriele Bavota",
                "Nicole Novielli",
                "Michele Lanza"
            ],
            "venue": "ACM Transactions on Software Engineering and Methodology (TOSEM)",
            "filename": "om-slr.pdf",
            "date": "2022-07-01"
        },
        {
            "id": "mixed",
            "type": "Conference",
            "title": "Human, Bot or Both? A study on the capabilities of classification models on mixed accounts",
            "authors": [
                "Nathan Cassee",
                "Christos Kitsanelis",
                "Eleni Constantinou",
                "Alexander Serebrenik"
            ],
            "venue": "International Conference on Software Maintenance and Evolution (ICSME), NIER Track",
            "filename": "bot_or_not.pdf",
            "date": "2021-09-28"
        },
        {
            "id": "satd-and-polarity",
            "type": "Journal",
            "title": "Self-Admitted Technical Debt and Comments' Polarity: An Empirical Study",
            "authors": [
                "Nathan Cassee",
                "Fiorella Zampetti",
                "Nicole Novielli",
                "Alexander Serebrenik",
                "Massimiliano Di Penta"
            ],
            "venue": "Empirical Software Engineering (EMSE)",
            "filename": "satd-and-polarity.pdf",
            "date": "2022-05-28"
        },
        {
            "id": "esec-fse-doctoral",
            "type": "Conference",
            "title": "Sentiment in Software Engineering: Detection and Application",
            "authors": [
                "Nathan Cassee"
            ],
            "venue": "ACM Joint European Software Engineering Conference and Symposium on the Foundations of Software Engineering (ESEC/FSE), Doctoral Symposium",
            "filename": "esec-fse-doctoral.pdf",
            "date": "2022-11-17"
        },
        {
            "id": "satd-sentiment",
            "type": "Conference",
            "title": "Waiting around or job half-done? Sentiment in Self-Admitted Technical Debt",
            "authors": [
                "Gianmarco Fucci",
                "Nathan Cassee",
                "Nicole Novielli",
                "Fiorella Zampetti",
                "Alexander Serebrenik",
                "Massimiliano Di Penta"
            ],
            "venue": "IEEE/ACM International Conference on Mining Software Repositories (MSR)",
            "filename": "waiting-around.pdf",
            "date": "2021-5-17"
        },
        {
            "id": "ci-helper",
            "type": "Conference",
            "title": "The Silent Helper: The Impact of Continuous Integration on Code Reviews",
            "authors": [
                "Nathan Cassee",
                "Bogdan Vasilescu",
                "Alexander Serebrenik"
            ],
            "venue": "IEEE International Conference on Software Analysis, Evolution and Reengineering (SANER)",
            "filename": "CI-silent.pdf",
            "date": "2020-1-18"
        },
        {
            "id": "swift-errors",
            "type": "Conference",
            "title": "How Swift developers handle errors",
            "authors": [
                "Nathan Cassee",
                "Gustavo Pinto",
                "Fernando Castor",
                "Alexander Serebrenik"
            ],
            "venue": "IEEE/ACM International Conference on Mining Software Repositories (MSR)",
            "filename": "swift_errors.pdf",
            "date": "2018-5-27"
        },
        {
            "id": "gpu-hashtables",
            "type": "Workshop",
            "title": "Analysing the performance of GPU hash tables for state space exploration",
            "authors": [
                "Nathan Cassee",
                "Anton Wijs"
            ],
            "venue": "Graphs as Models (GAM)",
            "filename": "gpu-hashtables.pdf",
            "date": "2017-12-27"
        },
        {
            "id": "gpuexplore-scalability",
            "type": "Workshop",
            "title": "On the scalability of the gpuexplore explicit-state model checker",
            "authors": [
                "Nathan Cassee",
                "Thomas Neele",
                "Anton Wijs"
            ],
            "venue": "Graphs as Models (GAM)",
            "filename": "gpuexplore-scalability.pdf",
            "date": "2017-12-27"
        },
        {
            "id": "phd-thesis", 
            "type": "Thesis",
            "title": "Sentiment in Software Engineering",
            "authors": [
                "Nathan Cassee"
            ],
            "filename": "PhD_Thesis_Nathan_Cassee.pdf",
            "date": "2024-10-31"
        },
        {
            "id": "empirical-teaching-chapter",
            "type": "Chapter",
            "title": "Teaching Empirical Methods at Eindhoven University of Technology",
            "authors": [
                "Alexander Serebrenik",
                "Nathan Cassee"
            ],
            "filename": "empirical-teaching-chapter.pdf",
            "date": "2024-08-01"
        }, 
        {
            "id": "satd-sentiment-experiment",
            "type": "Journal",
            "title": "Negativity in Self-Admitted Technical Debt: How Sentiment Influences Prioritization",
            "authors": [
                "Nathan Cassee",
                "Neil Ernst",
                "Nicole Novielli",
                "Alexander Serebrenik"
            ],
            "filename": "Sentiment_in_SATD_pre_print.pdf",
            "venue": "Empirical Software Engineering (EMSE)",
            "date": "2024-12-29"
        }
    ]
}