{
    "data": 
    [
        {
            "type": "Conference Organization",
            "description": "Web Co-Chair for the 21st International Conference on Mining Software Repositories (MSR)",
            "year": 2024
        },
        {
            "type":"Program Committee",
            "description": "ICSME-NIER track",
            "year": 2023
        },
        {
            "type": "Program Committee",
            "description": "BotSE workshop",
            "year": 2023
        },
        {
            "type": "Program Committee",
            "description": "NLBSE workshop",
            "year": 2023
        }, 
        {
            "type": "Program Committee",
            "description": "MSR Junior PC",
            "year": 2023
        },
        {
            "type": "Program Committee",
            "description": "MSR Junior PC",
            "year": 2021
        },
        {
            "type": "Conference Organization",
            "description": "Web Chair for Source Code Analysis and Manipulation (SCAM)",
            "year": 2021
        }
    ]
}